wkpdia/__init__.py
wkpdia/wkpdia.py
wkpdia-0.2.dist-info/METADATA
wkpdia-0.2.dist-info/WHEEL
wkpdia-0.2.dist-info/top_level.txt
wkpdia-0.2.dist-info/RECORD
