Metadata-Version: 2.1
Name: wkpdia
Version: 0.2
Summary: Wikipedia downloader and parser in Python
Author: Hansimov
Project-URL: Homepage, https://github.com/Hansimov/wkpdia
Project-URL: Issues, https://github.com/Hansimov/wkpdia/issues
Project-URL: CHANGELOG, https://github.com/Hansimov/wkpdia/blob/main/CHANGELOG.md
Classifier: Programming Language :: Python :: 3
Classifier: License :: OSI Approved :: MIT License
Classifier: Operating System :: OS Independent
Requires-Python: >=3.6
Requires-Dist: requests
Requires-Dist: purehtml
